<?xml version="1.0" encoding="UTF-8" standalone="yes"?>
<SimulationScenario xmlns="http://geography.environment" logUsed="true" displayUsed="true" scale="60" Ysize="15" Xsize="20" name="ClusteringEnvironment">
    <crowd>
        <goal y="3.0" x="14.6"/>
        <position y="2.9833333333333334" x="0.25"/>
        <id>1</id>
        <preferedSpeed>1.3</preferedSpeed>
        <commitmentLevel>2</commitmentLevel>
    </crowd>
    <crowd>
        <goal y="2.816666666666667" x="0.26666666666666666"/>
        <position y="2.8333333333333335" x="6.0"/>
        <id>2</id>
        <preferedSpeed>1.3</preferedSpeed>
        <commitmentLevel>2</commitmentLevel>
    </crowd>
    <crowd>
        <goal y="3.15" x="0.23333333333333334"/>
        <position y="3.05" x="5.683333333333334"/>
        <id>3</id>
        <preferedSpeed>1.3</preferedSpeed>
        <commitmentLevel>2</commitmentLevel>
    </crowd>
    <crowd>
        <goal y="3.2" x="0.18333333333333332"/>
        <position y="3.216666666666667" x="6.016666666666667"/>
        <id>4</id>
        <preferedSpeed>1.3</preferedSpeed>
        <commitmentLevel>2</commitmentLevel>
    </crowd>
    <crowd>
        <goal y="3.3666666666666667" x="0.25"/>
        <position y="3.3833333333333333" x="6.283333333333333"/>
        <id>5</id>
        <preferedSpeed>1.3</preferedSpeed>
        <commitmentLevel>2</commitmentLevel>
    </crowd>
    <crowd>
        <goal y="3.0166666666666666" x="0.26666666666666666"/>
        <position y="3.0166666666666666" x="6.283333333333333"/>
        <id>6</id>
        <preferedSpeed>1.3</preferedSpeed>
        <commitmentLevel>2</commitmentLevel>
    </crowd>
    <crowd>
        <goal y="2.6666666666666665" x="0.4166666666666667"/>
        <position y="2.65" x="6.483333333333333"/>
        <id>7</id>
        <preferedSpeed>1.3</preferedSpeed>
        <commitmentLevel>2</commitmentLevel>
    </crowd>
    <crowd>
        <goal y="2.716666666666667" x="0.4166666666666667"/>
        <position y="2.7333333333333334" x="9.8"/>
        <id>8</id>
        <preferedSpeed>1.3</preferedSpeed>
        <commitmentLevel>2</commitmentLevel>
    </crowd>
    <crowd>
        <goal y="2.5" x="0.31666666666666665"/>
        <position y="2.466666666666667" x="10.033333333333333"/>
        <id>9</id>
        <preferedSpeed>1.3</preferedSpeed>
        <commitmentLevel>2</commitmentLevel>
    </crowd>
    <crowd>
        <goal y="2.9" x="0.13333333333333333"/>
        <position y="2.8666666666666667" x="10.116666666666667"/>
        <id>10</id>
        <preferedSpeed>1.3</preferedSpeed>
        <commitmentLevel>2</commitmentLevel>
    </crowd>
    <crowd>
        <goal y="2.6" x="0.55"/>
        <position y="2.6" x="10.5"/>
        <id>11</id>
        <preferedSpeed>1.3</preferedSpeed>
        <commitmentLevel>2</commitmentLevel>
    </crowd>
    <crowd>
        <goal y="3.183333333333333" x="0.48333333333333334"/>
        <position y="3.183333333333333" x="12.433333333333334"/>
        <id>12</id>
        <preferedSpeed>1.3</preferedSpeed>
        <commitmentLevel>2</commitmentLevel>
    </crowd>
    <crowd>
        <goal y="3.3666666666666667" x="0.35"/>
        <position y="3.35" x="12.716666666666667"/>
        <id>13</id>
        <preferedSpeed>1.3</preferedSpeed>
        <commitmentLevel>2</commitmentLevel>
    </crowd>
    <crowd>
        <goal y="3.566666666666667" x="0.3"/>
        <position y="3.5833333333333335" x="12.45"/>
        <id>14</id>
        <preferedSpeed>1.3</preferedSpeed>
        <commitmentLevel>2</commitmentLevel>
    </crowd>
    <crowd>
        <goal y="3.4" x="0.38333333333333336"/>
        <position y="3.4" x="12.066666666666666"/>
        <id>15</id>
        <preferedSpeed>1.3</preferedSpeed>
        <commitmentLevel>2</commitmentLevel>
    </crowd>
</SimulationScenario>
